jsona/__init__.py
pyjsona-0.1.dist-info/METADATA
pyjsona-0.1.dist-info/RECORD
pyjsona-0.1.dist-info/WHEEL
pyjsona-0.1.dist-info/top_level.txt
