Metadata-Version: 2.1
Name: pyjsona
Version: 0.1
Summary: Package for flattening JSON API 1.0 responses into easy to use dict & list.
Home-page: https://github.com/TransparentTechnologies/pyJSONA
Author: Ryan Bonham
Author-email: ryan@transparent-tech.com
License: MIT
Platform: UNKNOWN
Requires-Python: >=3.6
